_8a_scraper/__init__.py
_8a_scraper/ascents.py
_8a_scraper/users.py
_8a_scraper/utils.py
test/__init__.py
test/test_ascents.py
test/test_users.py
8a_scraper-0.0.4.dist-info/LICENSE
8a_scraper-0.0.4.dist-info/METADATA
8a_scraper-0.0.4.dist-info/WHEEL
8a_scraper-0.0.4.dist-info/top_level.txt
8a_scraper-0.0.4.dist-info/RECORD
