Metadata-Version: 2.1
Name: 8a-scraper
Version: 0.0.4
Summary: A Python client for scraping data from 8a.nu
Home-page: https://github.com/vishaalagartha/8a_scraper
Author: Vishaal Agartha
Author-email: vishaalagartha@gmail.com
License: MIT
Keywords: climbing,rockclimbing,bouldering,sportclimbing,8a,8a.nu,data mining
Platform: UNKNOWN
Classifier: Programming Language :: Python :: 3
Classifier: License :: OSI Approved :: MIT License
Classifier: Operating System :: OS Independent
Requires-Python: >=3.6
Requires-Dist: beautifulsoup4 (==4.9.1)
Requires-Dist: bs4 (==0.0.1)
Requires-Dist: certifi (==2020.6.20)
Requires-Dist: chardet (==3.0.4)
Requires-Dist: idna (==2.10)
Requires-Dist: python-slugify (==4.0.1)
Requires-Dist: requests (==2.24.0)
Requires-Dist: selenium (==3.141.0)
Requires-Dist: soupsieve (==2.0.1)
Requires-Dist: urllib3 (==1.25.9)
Requires-Dist: webdriver-manager (==3.2.2)
Provides-Extra: test
Requires-Dist: unittest ; extra == 'test'
